swarmauri_certs_ocspverify/OcspVerifyService.py
swarmauri_certs_ocspverify/__init__.py
swarmauri_certs_ocspverify-0.9.0.dev4.dist-info/LICENSE
swarmauri_certs_ocspverify-0.9.0.dev4.dist-info/METADATA
swarmauri_certs_ocspverify-0.9.0.dev4.dist-info/WHEEL
swarmauri_certs_ocspverify-0.9.0.dev4.dist-info/entry_points.txt
swarmauri_certs_ocspverify-0.9.0.dev4.dist-info/RECORD
