Metadata-Version: 2.3
Name: swarmauri_certs_ocspverify
Version: 0.9.0.dev4
Summary: OCSP certificate verification service for Swarmauri.
License: Apache-2.0
Author: Jacob Stewart
Author-email: jacob@swarmauri.com
Requires-Python: >=3.10,<3.13
Classifier: License :: OSI Approved :: Apache Software License
Classifier: Programming Language :: Python :: 3.10
Classifier: Programming Language :: Python :: 3.11
Classifier: Programming Language :: Python :: 3.12
Provides-Extra: dev
Requires-Dist: cryptography (>=41.0.0)
Requires-Dist: httpx (>=0.27.0)
Requires-Dist: pytest (>=8.0) ; extra == "dev"
Requires-Dist: pytest-asyncio (>=0.24.0) ; extra == "dev"
Requires-Dist: swarmauri_base
Requires-Dist: swarmauri_core
Requires-Dist: swarmauri_standard
